Kungeekui/README.md
Kungeekui/__init__.py
Kungeekui/__main__.py
Kungeekui/file.epub
Kungeekui/index.html
Kungeekui/css/__init__.py
Kungeekui/css/annotations.css
Kungeekui/css/main.css
Kungeekui/css/normalize.css
Kungeekui/css/popup.css
Kungeekui/font/__init__.py
Kungeekui/font/fontello.eot
Kungeekui/font/fontello.svg
Kungeekui/font/fontello.ttf
Kungeekui/font/fontello.woff
Kungeekui/img/__init__.py
Kungeekui/img/annotator-glyph-sprite.png
Kungeekui/img/annotator-icon-sprite.png
Kungeekui/img/apple-touch-icon.png
Kungeekui/img/cancelfullscreen.png
Kungeekui/img/close.png
Kungeekui/img/fullscreen.png
Kungeekui/img/loader.gif
Kungeekui/img/menu-icon.png
Kungeekui/img/save.png
Kungeekui/img/saved.png
Kungeekui/img/settings-s.png
Kungeekui/img/settings.png
Kungeekui/img/star.png
Kungeekui/js/__init__.py
Kungeekui/js/epub.js
Kungeekui/js/epub.min.js
Kungeekui/js/epub.min.map
Kungeekui/js/hooks.min.js
Kungeekui/js/hooks.min.map
Kungeekui/js/reader.js
Kungeekui/js/reader.js.map
Kungeekui/js/reader.min.js
Kungeekui/js/reader.min.map
Kungeekui/js/hooks/__init__.py
Kungeekui/js/hooks/extensions/__init__.py
Kungeekui/js/hooks/extensions/highlight.js
Kungeekui/js/libs/__init__.py
Kungeekui/js/libs/jquery.min.js
Kungeekui/js/libs/localforage.min.js
Kungeekui/js/libs/screenfull.js
Kungeekui/js/libs/screenfull.min.js
Kungeekui/js/libs/zip.min.js
Kungeekui/js/plugins/__init__.py
Kungeekui/js/plugins/hypothesis.js
Kungeekui/js/plugins/search.js
kungeekui-2024.3.3.0.dist-info/METADATA
kungeekui-2024.3.3.0.dist-info/WHEEL
kungeekui-2024.3.3.0.dist-info/entry_points.txt
kungeekui-2024.3.3.0.dist-info/top_level.txt
kungeekui-2024.3.3.0.dist-info/RECORD
